numthreads.py
numthreads-0.6.1.dist-info/licenses/LICENSE
numthreads-0.6.1.dist-info/METADATA
numthreads-0.6.1.dist-info/WHEEL
numthreads-0.6.1.dist-info/entry_points.txt
numthreads-0.6.1.dist-info/top_level.txt
numthreads-0.6.1.dist-info/RECORD
